eps_entropy/__init__.py
eps_entropy/_version.py
eps_entropy/entropy.py
eps_entropy/symbols.py
eps_entropy/utils.py
eps_entropy-0.0.2.dist-info/DESCRIPTION.rst
eps_entropy-0.0.2.dist-info/METADATA
eps_entropy-0.0.2.dist-info/RECORD
eps_entropy-0.0.2.dist-info/WHEEL
eps_entropy-0.0.2.dist-info/metadata.json
eps_entropy-0.0.2.dist-info/top_level.txt
